agentensor/__init__.py
agentensor/loss.py
agentensor/module.py
agentensor/optim.py
agentensor/py.typed
agentensor/tensor.py
agentensor/train.py
agentensor-0.1.0.dist-info/METADATA
agentensor-0.1.0.dist-info/WHEEL
agentensor-0.1.0.dist-info/RECORD
