Metadata-Version: 2.4
Name: agentensor
Version: 0.1.0
Summary: Agent prompt tensors, modules, and optimizers for Orcheo workflows
Requires-Python: >=3.12
Requires-Dist: datasets>=3.5.0
Requires-Dist: langchain-ollama>=0.3.3
Requires-Dist: langchain-openai>=0.3.18
Requires-Dist: langchain>=1.1.3
Requires-Dist: langgraph>=1.0.5
Requires-Dist: logfire>=3.14.0
Requires-Dist: pydantic-ai>=0.2.4
Provides-Extra: dev
Requires-Dist: bump2version; extra == 'dev'
Requires-Dist: diff-cover>=9.2.4; extra == 'dev'
Requires-Dist: mypy>=1.11.2; extra == 'dev'
Requires-Dist: pre-commit; extra == 'dev'
Requires-Dist: pytest; extra == 'dev'
Requires-Dist: pytest-asyncio>=0.23.8; extra == 'dev'
Requires-Dist: pytest-cov>=4.1.0; extra == 'dev'
Requires-Dist: ruff>=0.11.3; extra == 'dev'
Requires-Dist: smokeshow>=0.5.0; extra == 'dev'
Requires-Dist: types-requests; extra == 'dev'
Provides-Extra: docs
Requires-Dist: mkdocs; extra == 'docs'
Requires-Dist: mkdocs-gen-files; extra == 'docs'
Requires-Dist: mkdocs-jupyter; extra == 'docs'
Requires-Dist: mkdocs-material; extra == 'docs'
Requires-Dist: mkdocstrings[python]>=0.28.1; extra == 'docs'
